imagetocsv/__init__.py
imagetocsv/cli.py
imagetocsv/hardcoded_options.py
imagetocsv/imagetocsv.py
imagetocsv/pathing.py
imagetocsv/string_modifiers.py
imagetocsv/tempfile.py
imagetocsv/examples/__init__.py
imagetocsv-1.0.0.dist-info/LICENSE
imagetocsv-1.0.0.dist-info/METADATA
imagetocsv-1.0.0.dist-info/WHEEL
imagetocsv-1.0.0.dist-info/entry_points.txt
imagetocsv-1.0.0.dist-info/top_level.txt
imagetocsv-1.0.0.dist-info/RECORD
