Metadata-Version: 2.1
Name: imagetocsv
Version: 1.0.0
Summary: Converts An Image to a CSV. This exists because Chorus 3.0 are bat-shit and only show images for vital metadata.
Home-page: https://github.com/tmsincomb/imagetocsv
Author: Troy Sincomb
Author-email: troysincomb@gmail.com
License: MIT license
Keywords: imagetocsv
Classifier: Development Status :: 4 - Beta
Classifier: Intended Audience :: Developers
Classifier: License :: OSI Approved :: MIT License
Classifier: Natural Language :: English
Classifier: Programming Language :: Python :: 3
Classifier: Programming Language :: Python :: 3.7
Classifier: Programming Language :: Python :: 3.8
Classifier: Programming Language :: Python :: 3.8
Classifier: Programming Language :: Python :: 3.9
Classifier: Programming Language :: Python :: 3.10
Classifier: Programming Language :: Python :: 3.11
Requires-Python: >=3.7
License-File: LICENSE
Requires-Dist: Click
Requires-Dist: pandas
Requires-Dist: opencv-python
Requires-Dist: pytesseract
Requires-Dist: pdftotext
Requires-Dist: tabulate
Provides-Extra: dev
Requires-Dist: pytest ; extra == 'dev'
Requires-Dist: pre-commit ; extra == 'dev'
Requires-Dist: twine ; extra == 'dev'
Requires-Dist: wheel ; extra == 'dev'
Requires-Dist: setuptools ; extra == 'dev'
